emailcompat32crlf/__init__.py
emailcompat32crlf-1.0.3.dist-info/METADATA
emailcompat32crlf-1.0.3.dist-info/WHEEL
emailcompat32crlf-1.0.3.dist-info/entry_points.txt
emailcompat32crlf-1.0.3.dist-info/top_level.txt
emailcompat32crlf-1.0.3.dist-info/RECORD
