Metadata-Version: 2.1
Name: emailcompat32crlf
Version: 1.0.3
Summary: Patch stdlib email compat32 policy to default to CRLF line endings.
Home-page: https://github.com/collective/emailcompat32crlf
Author: Guido Stevens
Author-email: guido.stevens@cosent.net
License: MIT
Keywords: email
Classifier: Development Status :: 4 - Beta
Classifier: License :: OSI Approved :: MIT License
Classifier: Programming Language :: Python :: 3
Classifier: Programming Language :: Python :: 3.8
Classifier: Programming Language :: Python :: 3.9
Classifier: Programming Language :: Python :: 3.10
Classifier: Programming Language :: Python :: 3.11
Classifier: Programming Language :: Python :: 3.12
Classifier: Topic :: Communications :: Email
Requires-Python: >=3.8
